{
	"name": "df_po_headers_all_flattening",
	"properties": {
		"folder": {
			"name": "Projects/Payment Dashboard/Po Headers All"
		},
		"type": "MappingDataFlow",
		"typeProperties": {
			"sources": [
				{
					"dataset": {
						"referenceName": "ds_adlsg2_xml_po_headers_all_source_stage_decoded_xml",
						"type": "DatasetReference"
					},
					"name": "SrcXMl"
				}
			],
			"sinks": [
				{
					"dataset": {
						"referenceName": "ds_adlsg2_csv_po_headers_all_source_stage_final_csv",
						"type": "DatasetReference"
					},
					"name": "SnkCsv"
				}
			],
			"transformations": [
				{
					"name": "XmlToCsvflatten"
				},
				{
					"name": "addLoadDetails"
				}
			],
			"scriptLines": [
				"source(output(",
				"          DATA_DS as (G_1 as (ACCEPTANCE_DUE_DATE as string, ACCEPTANCE_REQUIRED_FLAG as string, ACCEPTANCE_WITHIN_DAYS as short, ACTIVE_VERSION_FLAG as boolean, AGENT_ID as long, AGING_ONSET_POINT as string, AGING_PERIOD_DAYS as string, ALLOW_MULTIPLE_SITES_FLAG as boolean, ALT_CONTACT_EMAIL_ADDRESS as string, AMOUNT_LIMIT as string, AMOUNT_RELEASED as string, APPROVED_DATE as string, APPROVED_FLAG as boolean, ATTRIBUTE1 as string, ATTRIBUTE10 as string, ATTRIBUTE11 as string, ATTRIBUTE12 as string, ATTRIBUTE13 as string, ATTRIBUTE14 as string, ATTRIBUTE15 as boolean, ATTRIBUTE16 as string, ATTRIBUTE17 as boolean, ATTRIBUTE18 as string, ATTRIBUTE19 as string, ATTRIBUTE2 as string, ATTRIBUTE20 as string, ATTRIBUTE3 as string, ATTRIBUTE4 as string, ATTRIBUTE5 as string, ATTRIBUTE6 as string, ATTRIBUTE7 as string, ATTRIBUTE8 as string, ATTRIBUTE9 as boolean, ATTRIBUTE_CATEGORY as string, ATTRIBUTE_DATE1 as string, ATTRIBUTE_DATE10 as string, ATTRIBUTE_DATE2 as string, ATTRIBUTE_DATE3 as string, ATTRIBUTE_DATE4 as string, ATTRIBUTE_DATE5 as string, ATTRIBUTE_DATE6 as string, ATTRIBUTE_DATE7 as string, ATTRIBUTE_DATE8 as string, ATTRIBUTE_DATE9 as string, ATTRIBUTE_NUMBER1 as string, ATTRIBUTE_NUMBER10 as string, ATTRIBUTE_NUMBER2 as string, ATTRIBUTE_NUMBER3 as string, ATTRIBUTE_NUMBER4 as string, ATTRIBUTE_NUMBER5 as string, ATTRIBUTE_NUMBER6 as string, ATTRIBUTE_NUMBER7 as string, ATTRIBUTE_NUMBER8 as string, ATTRIBUTE_NUMBER9 as string, ATTRIBUTE_TIMESTAMP1 as string, ATTRIBUTE_TIMESTAMP10 as string, ATTRIBUTE_TIMESTAMP2 as string, ATTRIBUTE_TIMESTAMP3 as string, ATTRIBUTE_TIMESTAMP4 as string, ATTRIBUTE_TIMESTAMP5 as string, ATTRIBUTE_TIMESTAMP6 as string, ATTRIBUTE_TIMESTAMP7 as string, ATTRIBUTE_TIMESTAMP8 as string, ATTRIBUTE_TIMESTAMP9 as string, AUTO_SOURCING_FLAG as string, BCC_EMAIL_ADDRESS as string, BILLING_CYCLE_CLOSING_DATE as string, BILLTO_BU_ID as long, BILL_TO_LOCATION_ID as long, BLANKET_TOTAL_AMOUNT as string, BUDGET_CONTROL_ENABLED_FLAG as string, BUYER_MANAGED_TRANSPORT_FLAG as boolean, CANCEL_FLAG as string, CARRIER_ID as long, CAT_ADMIN_AUTH_ENABLED_FLAG as boolean, CBC_ACCOUNTING_DATE as string, CC_EMAIL_ADDRESS as string, CHANGE_REQUESTED_BY as string, CHANGE_SUMMARY as string, CHECKLIST_ID as string, CLOSED_DATE as string, COMMENTS as string, CONFIRMING_ORDER_FLAG as boolean, CONSIGNED_CONSUMPTION_FLAG as string, CONSUME_REQ_DEMAND_FLAG as boolean, CONSUMPTION_ADVICE_FREQUENCY as string, CONSUMPTION_ADVICE_SUMMARY as string, CONTERMS_ARTICLES_UPD_DATE as string, CONTERMS_DELIV_UPD_DATE as string, CONTERMS_EXIST_FLAG as boolean, CPA_REFERENCE as string, CREATED_BY as string, CREATED_LANGUAGE as string, CREATION_DATE as string, CURRENCY_CODE as string, CURRENT_VERSION_ID as long, DEFAULT_CONSIGNMENT_LINE_FLAG as boolean, DEFAULT_PO_TRADE_ORG_ID as string, DEFAULT_TAXATION_COUNTRY as string, DISABLE_AUTOSOURCING_FLAG as boolean, DOCUMENT_CREATION_METHOD as string, DOCUMENT_STATUS as string, EDI_PROCESSED_FLAG as string, EDI_PROCESSED_STATUS as string, EMAIL_ADDRESS as string, ENABLED_FLAG as boolean, ENCUMBRANCE_REQUIRED_FLAG as string, END_DATE as string, FAX as long, FIRM_DATE as string, FIRM_STATUS_LOOKUP_CODE as boolean, FIRST_PTY_REG_ID as string, FOB_LOOKUP_CODE as string, FREIGHT_TERMS_LOOKUP_CODE as string, FROM_HEADER_ID as string, FROM_TYPE_LOOKUP_CODE as string, FROZEN_FLAG as string, FUNDS_STATUS as string, GENERATE_ORDERS_AUTOMATIC as boolean, GLOBAL_ATTRIBUTE1 as string, GLOBAL_ATTRIBUTE10 as string, GLOBAL_ATTRIBUTE11 as string, GLOBAL_ATTRIBUTE12 as string, GLOBAL_ATTRIBUTE13 as string, GLOBAL_ATTRIBUTE14 as string, GLOBAL_ATTRIBUTE15 as string, GLOBAL_ATTRIBUTE16 as string, GLOBAL_ATTRIBUTE17 as string, GLOBAL_ATTRIBUTE18 as string, GLOBAL_ATTRIBUTE19 as string, GLOBAL_ATTRIBUTE2 as string, GLOBAL_ATTRIBUTE20 as string, GLOBAL_ATTRIBUTE3 as string, GLOBAL_ATTRIBUTE4 as string, GLOBAL_ATTRIBUTE5 as string, GLOBAL_ATTRIBUTE6 as string, GLOBAL_ATTRIBUTE7 as string, GLOBAL_ATTRIBUTE8 as string, GLOBAL_ATTRIBUTE9 as string, GLOBAL_ATTRIBUTE_CATEGORY as string, GLOBAL_ATTRIBUTE_DATE1 as string, GLOBAL_ATTRIBUTE_DATE2 as string, GLOBAL_ATTRIBUTE_DATE3 as string, GLOBAL_ATTRIBUTE_DATE4 as string, GLOBAL_ATTRIBUTE_DATE5 as string, GLOBAL_ATTRIBUTE_NUMBER1 as string, GLOBAL_ATTRIBUTE_NUMBER2 as string, GLOBAL_ATTRIBUTE_NUMBER3 as string, GLOBAL_ATTRIBUTE_NUMBER4 as string, GLOBAL_ATTRIBUTE_NUMBER5 as string, GOVERNMENT_CONTEXT as string, GROUP_REQUISITIONS as boolean, GROUP_REQUISITION_LINES as boolean, INTERFACE_SOURCE_CODE as string, JOB_DEFINITION_NAME as string, JOB_DEFINITION_PACKAGE as string, LAST_BILLED_DATE as string, LAST_RELEASE_DATE as string, LAST_UPDATED_BY as string, LAST_UPDATED_PROGRAM as string, LAST_UPDATE_DATE as string, LAST_UPDATE_LOGIN as string, MASTER_CONTRACT_ID as string, MERGE_REQUEST_ID as string, MIN_RELEASE_AMOUNT as string, MODE_OF_TRANSPORT as string, NOTE_TO_AUTHORIZER as string, NOTE_TO_RECEIVER as string, NOTE_TO_VENDOR as string, OBJECT_VERSION_NUMBER as short, ORCHESTRATION_ORDER_FLAG as boolean, OVERRIDING_APPROVER_ID as string, PAY_ON_CODE as string, PAY_ON_USE_FLAG as boolean, PCARD_ID as string, PENDING_SIGNATURE_FLAG as string, PO_HEADER_ID as long, PRC_BU_ID as long, PRICE_UPDATE_TOLERANCE as string, PROGRAM_APP_NAME as string, PROGRAM_NAME as string, PUNCHOUT_SOURCING_ONLY_FLAG as string, RATE as double, RATE_DATE as string, RATE_TYPE as string, REBUILD_INDEX as string, REFERENCE_NUM as string, REFRESH_INDEX as string, RELEASE_METHOD as string, REQUEST_ID as integer, REQ_BU_ID as long, RETRO_PRICE_APPLY_UPDATES_FLAG as boolean, RETRO_PRICE_COMM_UPDATES_FLAG as boolean, RETRO_PRICE_INIT_APPROVAL_FLAG as string, RETRO_PRICE_OPEN_ORDER_FLAG as boolean, REVIEW_AUTOGENERATED_RELEASES as string, REVISED_DATE as string, REVISION_NUM as short, SCHEDULE_GROUP as string, SEGMENT1 as string, SEGMENT2 as string, SEGMENT3 as string, SEGMENT4 as string, SEGMENT5 as string, SERVICE_LEVEL as string, SHIPPING_CONTROL as string, SHIP_TO_LOCATION_ID as long, SH_ATTRIBUTE1 as string, SH_ATTRIBUTE10 as string, SH_ATTRIBUTE11 as string, SH_ATTRIBUTE12 as string, SH_ATTRIBUTE13 as string, SH_ATTRIBUTE14 as string, SH_ATTRIBUTE15 as string, SH_ATTRIBUTE16 as string, SH_ATTRIBUTE17 as string, SH_ATTRIBUTE18 as string, SH_ATTRIBUTE19 as string, SH_ATTRIBUTE2 as string, SH_ATTRIBUTE20 as string, SH_ATTRIBUTE3 as string, SH_ATTRIBUTE4 as string, SH_ATTRIBUTE5 as string, SH_ATTRIBUTE6 as string, SH_ATTRIBUTE7 as string, SH_ATTRIBUTE8 as string, SH_ATTRIBUTE9 as string, SH_ATTRIBUTE_CATEGORY as string, SH_ATTRIBUTE_DATE1 as string, SH_ATTRIBUTE_DATE10 as string, SH_ATTRIBUTE_DATE2 as string, SH_ATTRIBUTE_DATE3 as string, SH_ATTRIBUTE_DATE4 as string, SH_ATTRIBUTE_DATE5 as string, SH_ATTRIBUTE_DATE6 as string, SH_ATTRIBUTE_DATE7 as string, SH_ATTRIBUTE_DATE8 as string, SH_ATTRIBUTE_DATE9 as string, SH_ATTRIBUTE_NUMBER1 as string, SH_ATTRIBUTE_NUMBER10 as string, SH_ATTRIBUTE_NUMBER2 as string, SH_ATTRIBUTE_NUMBER3 as string, SH_ATTRIBUTE_NUMBER4 as string, SH_ATTRIBUTE_NUMBER5 as string, SH_ATTRIBUTE_NUMBER6 as string, SH_ATTRIBUTE_NUMBER7 as string, SH_ATTRIBUTE_NUMBER8 as string, SH_ATTRIBUTE_NUMBER9 as string, SH_ATTRIBUTE_TIMESTAMP1 as string, SH_ATTRIBUTE_TIMESTAMP10 as string, SH_ATTRIBUTE_TIMESTAMP2 as string, SH_ATTRIBUTE_TIMESTAMP3 as string, SH_ATTRIBUTE_TIMESTAMP4 as string, SH_ATTRIBUTE_TIMESTAMP5 as string, SH_ATTRIBUTE_TIMESTAMP6 as string, SH_ATTRIBUTE_TIMESTAMP7 as string, SH_ATTRIBUTE_TIMESTAMP8 as string, SH_ATTRIBUTE_TIMESTAMP9 as string, SIGNATURE_REQUIRED_FLAG as boolean, SKIP_ELECTRONIC_COMM_FLAG as boolean, SOLDTO_BU_ID as string, SOLDTO_LE_ID as long, SOURCING_PRIORITY as string, SPECIAL_HANDLING_TYPE_CODE as string, START_DATE as string, STYLE_ID as boolean, SUBMIT_APPROVAL_AUTOMATIC as boolean, SUBMIT_DATE as string, SUMMARY_FLAG as boolean, SUPPLIER_NOTIF_METHOD as string, TAX_ATTRIBUTE_UPDATE_CODE as string, TAX_DOCUMENT_SUBTYPE as string, TERMS_ID as long, THIRD_PTY_REG_ID as string, TYPE_LOOKUP_CODE as string, UPDATE_SOURCING_RULES_FLAG as string, USE_NEED_BY_DATE as boolean, USE_ORDER_DATE_IN_PRICING_FLAG as boolean, USE_SALES_ORDER_NUMBER_FLAG as boolean, USE_SHIP_TO as boolean, USE_SHIP_TO_FOR_GROUP_REQS as boolean, VENDOR_CONTACT_ID as long, VENDOR_ID as long, VENDOR_ORDER_NUM as string, VENDOR_SITE_ID as long, XML_CHANGE_SEND_DATE as string, XML_FLAG as string, XML_SEND_DATE as string)[])",
				"     ),",
				"     allowSchemaDrift: false,",
				"     validateSchema: false,",
				"     ignoreNoFilesFound: false,",
				"     validationMode: 'none',",
				"     namespaces: true) ~> SrcXMl",
				"SrcXMl foldDown(unroll(DATA_DS.G_1),",
				"     mapColumn(",
				"          ACCEPTANCE_DUE_DATE = DATA_DS.G_1.ACCEPTANCE_DUE_DATE,",
				"          ACCEPTANCE_REQUIRED_FLAG = DATA_DS.G_1.ACCEPTANCE_REQUIRED_FLAG,",
				"          ACCEPTANCE_WITHIN_DAYS = DATA_DS.G_1.ACCEPTANCE_WITHIN_DAYS,",
				"          ACTIVE_VERSION_FLAG = DATA_DS.G_1.ACTIVE_VERSION_FLAG,",
				"          AGENT_ID = DATA_DS.G_1.AGENT_ID,",
				"          AGING_ONSET_POINT = DATA_DS.G_1.AGING_ONSET_POINT,",
				"          AGING_PERIOD_DAYS = DATA_DS.G_1.AGING_PERIOD_DAYS,",
				"          ALLOW_MULTIPLE_SITES_FLAG = DATA_DS.G_1.ALLOW_MULTIPLE_SITES_FLAG,",
				"          ALT_CONTACT_EMAIL_ADDRESS = DATA_DS.G_1.ALT_CONTACT_EMAIL_ADDRESS,",
				"          AMOUNT_LIMIT = DATA_DS.G_1.AMOUNT_LIMIT,",
				"          AMOUNT_RELEASED = DATA_DS.G_1.AMOUNT_RELEASED,",
				"          APPROVED_DATE = DATA_DS.G_1.APPROVED_DATE,",
				"          APPROVED_FLAG = DATA_DS.G_1.APPROVED_FLAG,",
				"          ATTRIBUTE1 = DATA_DS.G_1.ATTRIBUTE1,",
				"          ATTRIBUTE10 = DATA_DS.G_1.ATTRIBUTE10,",
				"          ATTRIBUTE11 = DATA_DS.G_1.ATTRIBUTE11,",
				"          ATTRIBUTE12 = DATA_DS.G_1.ATTRIBUTE12,",
				"          ATTRIBUTE13 = DATA_DS.G_1.ATTRIBUTE13,",
				"          ATTRIBUTE14 = DATA_DS.G_1.ATTRIBUTE14,",
				"          ATTRIBUTE15 = DATA_DS.G_1.ATTRIBUTE15,",
				"          ATTRIBUTE16 = DATA_DS.G_1.ATTRIBUTE16,",
				"          ATTRIBUTE17 = DATA_DS.G_1.ATTRIBUTE17,",
				"          ATTRIBUTE18 = DATA_DS.G_1.ATTRIBUTE18,",
				"          ATTRIBUTE19 = DATA_DS.G_1.ATTRIBUTE19,",
				"          ATTRIBUTE2 = DATA_DS.G_1.ATTRIBUTE2,",
				"          ATTRIBUTE20 = DATA_DS.G_1.ATTRIBUTE20,",
				"          ATTRIBUTE3 = DATA_DS.G_1.ATTRIBUTE3,",
				"          ATTRIBUTE4 = DATA_DS.G_1.ATTRIBUTE4,",
				"          ATTRIBUTE5 = DATA_DS.G_1.ATTRIBUTE5,",
				"          ATTRIBUTE6 = DATA_DS.G_1.ATTRIBUTE6,",
				"          ATTRIBUTE7 = DATA_DS.G_1.ATTRIBUTE7,",
				"          ATTRIBUTE8 = DATA_DS.G_1.ATTRIBUTE8,",
				"          ATTRIBUTE9 = DATA_DS.G_1.ATTRIBUTE9,",
				"          ATTRIBUTE_CATEGORY = DATA_DS.G_1.ATTRIBUTE_CATEGORY,",
				"          ATTRIBUTE_DATE1 = DATA_DS.G_1.ATTRIBUTE_DATE1,",
				"          ATTRIBUTE_DATE10 = DATA_DS.G_1.ATTRIBUTE_DATE10,",
				"          ATTRIBUTE_DATE2 = DATA_DS.G_1.ATTRIBUTE_DATE2,",
				"          ATTRIBUTE_DATE3 = DATA_DS.G_1.ATTRIBUTE_DATE3,",
				"          ATTRIBUTE_DATE4 = DATA_DS.G_1.ATTRIBUTE_DATE4,",
				"          ATTRIBUTE_DATE5 = DATA_DS.G_1.ATTRIBUTE_DATE5,",
				"          ATTRIBUTE_DATE6 = DATA_DS.G_1.ATTRIBUTE_DATE6,",
				"          ATTRIBUTE_DATE7 = DATA_DS.G_1.ATTRIBUTE_DATE7,",
				"          ATTRIBUTE_DATE8 = DATA_DS.G_1.ATTRIBUTE_DATE8,",
				"          ATTRIBUTE_DATE9 = DATA_DS.G_1.ATTRIBUTE_DATE9,",
				"          ATTRIBUTE_NUMBER1 = DATA_DS.G_1.ATTRIBUTE_NUMBER1,",
				"          ATTRIBUTE_NUMBER10 = DATA_DS.G_1.ATTRIBUTE_NUMBER10,",
				"          ATTRIBUTE_NUMBER2 = DATA_DS.G_1.ATTRIBUTE_NUMBER2,",
				"          ATTRIBUTE_NUMBER3 = DATA_DS.G_1.ATTRIBUTE_NUMBER3,",
				"          ATTRIBUTE_NUMBER4 = DATA_DS.G_1.ATTRIBUTE_NUMBER4,",
				"          ATTRIBUTE_NUMBER5 = DATA_DS.G_1.ATTRIBUTE_NUMBER5,",
				"          ATTRIBUTE_NUMBER6 = DATA_DS.G_1.ATTRIBUTE_NUMBER6,",
				"          ATTRIBUTE_NUMBER7 = DATA_DS.G_1.ATTRIBUTE_NUMBER7,",
				"          ATTRIBUTE_NUMBER8 = DATA_DS.G_1.ATTRIBUTE_NUMBER8,",
				"          ATTRIBUTE_NUMBER9 = DATA_DS.G_1.ATTRIBUTE_NUMBER9,",
				"          ATTRIBUTE_TIMESTAMP1 = DATA_DS.G_1.ATTRIBUTE_TIMESTAMP1,",
				"          ATTRIBUTE_TIMESTAMP10 = DATA_DS.G_1.ATTRIBUTE_TIMESTAMP10,",
				"          ATTRIBUTE_TIMESTAMP2 = DATA_DS.G_1.ATTRIBUTE_TIMESTAMP2,",
				"          ATTRIBUTE_TIMESTAMP3 = DATA_DS.G_1.ATTRIBUTE_TIMESTAMP3,",
				"          ATTRIBUTE_TIMESTAMP4 = DATA_DS.G_1.ATTRIBUTE_TIMESTAMP4,",
				"          ATTRIBUTE_TIMESTAMP5 = DATA_DS.G_1.ATTRIBUTE_TIMESTAMP5,",
				"          ATTRIBUTE_TIMESTAMP6 = DATA_DS.G_1.ATTRIBUTE_TIMESTAMP6,",
				"          ATTRIBUTE_TIMESTAMP7 = DATA_DS.G_1.ATTRIBUTE_TIMESTAMP7,",
				"          ATTRIBUTE_TIMESTAMP8 = DATA_DS.G_1.ATTRIBUTE_TIMESTAMP8,",
				"          ATTRIBUTE_TIMESTAMP9 = DATA_DS.G_1.ATTRIBUTE_TIMESTAMP9,",
				"          AUTO_SOURCING_FLAG = DATA_DS.G_1.AUTO_SOURCING_FLAG,",
				"          BCC_EMAIL_ADDRESS = DATA_DS.G_1.BCC_EMAIL_ADDRESS,",
				"          BILLING_CYCLE_CLOSING_DATE = DATA_DS.G_1.BILLING_CYCLE_CLOSING_DATE,",
				"          BILLTO_BU_ID = DATA_DS.G_1.BILLTO_BU_ID,",
				"          BILL_TO_LOCATION_ID = DATA_DS.G_1.BILL_TO_LOCATION_ID,",
				"          BLANKET_TOTAL_AMOUNT = DATA_DS.G_1.BLANKET_TOTAL_AMOUNT,",
				"          BUDGET_CONTROL_ENABLED_FLAG = DATA_DS.G_1.BUDGET_CONTROL_ENABLED_FLAG,",
				"          BUYER_MANAGED_TRANSPORT_FLAG = DATA_DS.G_1.BUYER_MANAGED_TRANSPORT_FLAG,",
				"          CANCEL_FLAG = DATA_DS.G_1.CANCEL_FLAG,",
				"          CARRIER_ID = DATA_DS.G_1.CARRIER_ID,",
				"          CAT_ADMIN_AUTH_ENABLED_FLAG = DATA_DS.G_1.CAT_ADMIN_AUTH_ENABLED_FLAG,",
				"          CBC_ACCOUNTING_DATE = DATA_DS.G_1.CBC_ACCOUNTING_DATE,",
				"          CC_EMAIL_ADDRESS = DATA_DS.G_1.CC_EMAIL_ADDRESS,",
				"          CHANGE_REQUESTED_BY = DATA_DS.G_1.CHANGE_REQUESTED_BY,",
				"          CHANGE_SUMMARY = DATA_DS.G_1.CHANGE_SUMMARY,",
				"          CHECKLIST_ID = DATA_DS.G_1.CHECKLIST_ID,",
				"          CLOSED_DATE = DATA_DS.G_1.CLOSED_DATE,",
				"          COMMENTS = DATA_DS.G_1.COMMENTS,",
				"          CONFIRMING_ORDER_FLAG = DATA_DS.G_1.CONFIRMING_ORDER_FLAG,",
				"          CONSIGNED_CONSUMPTION_FLAG = DATA_DS.G_1.CONSIGNED_CONSUMPTION_FLAG,",
				"          CONSUME_REQ_DEMAND_FLAG = DATA_DS.G_1.CONSUME_REQ_DEMAND_FLAG,",
				"          CONSUMPTION_ADVICE_FREQUENCY = DATA_DS.G_1.CONSUMPTION_ADVICE_FREQUENCY,",
				"          CONSUMPTION_ADVICE_SUMMARY = DATA_DS.G_1.CONSUMPTION_ADVICE_SUMMARY,",
				"          CONTERMS_ARTICLES_UPD_DATE = DATA_DS.G_1.CONTERMS_ARTICLES_UPD_DATE,",
				"          CONTERMS_DELIV_UPD_DATE = DATA_DS.G_1.CONTERMS_DELIV_UPD_DATE,",
				"          CONTERMS_EXIST_FLAG = DATA_DS.G_1.CONTERMS_EXIST_FLAG,",
				"          CPA_REFERENCE = DATA_DS.G_1.CPA_REFERENCE,",
				"          CREATED_BY = DATA_DS.G_1.CREATED_BY,",
				"          CREATED_LANGUAGE = DATA_DS.G_1.CREATED_LANGUAGE,",
				"          CREATION_DATE = DATA_DS.G_1.CREATION_DATE,",
				"          CURRENCY_CODE = DATA_DS.G_1.CURRENCY_CODE,",
				"          CURRENT_VERSION_ID = DATA_DS.G_1.CURRENT_VERSION_ID,",
				"          DEFAULT_CONSIGNMENT_LINE_FLAG = DATA_DS.G_1.DEFAULT_CONSIGNMENT_LINE_FLAG,",
				"          DEFAULT_PO_TRADE_ORG_ID = DATA_DS.G_1.DEFAULT_PO_TRADE_ORG_ID,",
				"          DEFAULT_TAXATION_COUNTRY = DATA_DS.G_1.DEFAULT_TAXATION_COUNTRY,",
				"          DISABLE_AUTOSOURCING_FLAG = DATA_DS.G_1.DISABLE_AUTOSOURCING_FLAG,",
				"          DOCUMENT_CREATION_METHOD = DATA_DS.G_1.DOCUMENT_CREATION_METHOD,",
				"          DOCUMENT_STATUS = DATA_DS.G_1.DOCUMENT_STATUS,",
				"          EDI_PROCESSED_FLAG = DATA_DS.G_1.EDI_PROCESSED_FLAG,",
				"          EDI_PROCESSED_STATUS = DATA_DS.G_1.EDI_PROCESSED_STATUS,",
				"          EMAIL_ADDRESS = DATA_DS.G_1.EMAIL_ADDRESS,",
				"          ENABLED_FLAG = DATA_DS.G_1.ENABLED_FLAG,",
				"          ENCUMBRANCE_REQUIRED_FLAG = DATA_DS.G_1.ENCUMBRANCE_REQUIRED_FLAG,",
				"          END_DATE = DATA_DS.G_1.END_DATE,",
				"          FAX = DATA_DS.G_1.FAX,",
				"          FIRM_DATE = DATA_DS.G_1.FIRM_DATE,",
				"          FIRM_STATUS_LOOKUP_CODE = DATA_DS.G_1.FIRM_STATUS_LOOKUP_CODE,",
				"          FIRST_PTY_REG_ID = DATA_DS.G_1.FIRST_PTY_REG_ID,",
				"          FOB_LOOKUP_CODE = DATA_DS.G_1.FOB_LOOKUP_CODE,",
				"          FREIGHT_TERMS_LOOKUP_CODE = DATA_DS.G_1.FREIGHT_TERMS_LOOKUP_CODE,",
				"          FROM_HEADER_ID = DATA_DS.G_1.FROM_HEADER_ID,",
				"          FROM_TYPE_LOOKUP_CODE = DATA_DS.G_1.FROM_TYPE_LOOKUP_CODE,",
				"          FROZEN_FLAG = DATA_DS.G_1.FROZEN_FLAG,",
				"          FUNDS_STATUS = DATA_DS.G_1.FUNDS_STATUS,",
				"          GENERATE_ORDERS_AUTOMATIC = DATA_DS.G_1.GENERATE_ORDERS_AUTOMATIC,",
				"          GLOBAL_ATTRIBUTE1 = DATA_DS.G_1.GLOBAL_ATTRIBUTE1,",
				"          GLOBAL_ATTRIBUTE10 = DATA_DS.G_1.GLOBAL_ATTRIBUTE10,",
				"          GLOBAL_ATTRIBUTE11 = DATA_DS.G_1.GLOBAL_ATTRIBUTE11,",
				"          GLOBAL_ATTRIBUTE12 = DATA_DS.G_1.GLOBAL_ATTRIBUTE12,",
				"          GLOBAL_ATTRIBUTE13 = DATA_DS.G_1.GLOBAL_ATTRIBUTE13,",
				"          GLOBAL_ATTRIBUTE14 = DATA_DS.G_1.GLOBAL_ATTRIBUTE14,",
				"          GLOBAL_ATTRIBUTE15 = DATA_DS.G_1.GLOBAL_ATTRIBUTE15,",
				"          GLOBAL_ATTRIBUTE16 = DATA_DS.G_1.GLOBAL_ATTRIBUTE16,",
				"          GLOBAL_ATTRIBUTE17 = DATA_DS.G_1.GLOBAL_ATTRIBUTE17,",
				"          GLOBAL_ATTRIBUTE18 = DATA_DS.G_1.GLOBAL_ATTRIBUTE18,",
				"          GLOBAL_ATTRIBUTE19 = DATA_DS.G_1.GLOBAL_ATTRIBUTE19,",
				"          GLOBAL_ATTRIBUTE2 = DATA_DS.G_1.GLOBAL_ATTRIBUTE2,",
				"          GLOBAL_ATTRIBUTE20 = DATA_DS.G_1.GLOBAL_ATTRIBUTE20,",
				"          GLOBAL_ATTRIBUTE3 = DATA_DS.G_1.GLOBAL_ATTRIBUTE3,",
				"          GLOBAL_ATTRIBUTE4 = DATA_DS.G_1.GLOBAL_ATTRIBUTE4,",
				"          GLOBAL_ATTRIBUTE5 = DATA_DS.G_1.GLOBAL_ATTRIBUTE5,",
				"          GLOBAL_ATTRIBUTE6 = DATA_DS.G_1.GLOBAL_ATTRIBUTE6,",
				"          GLOBAL_ATTRIBUTE7 = DATA_DS.G_1.GLOBAL_ATTRIBUTE7,",
				"          GLOBAL_ATTRIBUTE8 = DATA_DS.G_1.GLOBAL_ATTRIBUTE8,",
				"          GLOBAL_ATTRIBUTE9 = DATA_DS.G_1.GLOBAL_ATTRIBUTE9,",
				"          GLOBAL_ATTRIBUTE_CATEGORY = DATA_DS.G_1.GLOBAL_ATTRIBUTE_CATEGORY,",
				"          GLOBAL_ATTRIBUTE_DATE1 = DATA_DS.G_1.GLOBAL_ATTRIBUTE_DATE1,",
				"          GLOBAL_ATTRIBUTE_DATE2 = DATA_DS.G_1.GLOBAL_ATTRIBUTE_DATE2,",
				"          GLOBAL_ATTRIBUTE_DATE3 = DATA_DS.G_1.GLOBAL_ATTRIBUTE_DATE3,",
				"          GLOBAL_ATTRIBUTE_DATE4 = DATA_DS.G_1.GLOBAL_ATTRIBUTE_DATE4,",
				"          GLOBAL_ATTRIBUTE_DATE5 = DATA_DS.G_1.GLOBAL_ATTRIBUTE_DATE5,",
				"          GLOBAL_ATTRIBUTE_NUMBER1 = DATA_DS.G_1.GLOBAL_ATTRIBUTE_NUMBER1,",
				"          GLOBAL_ATTRIBUTE_NUMBER2 = DATA_DS.G_1.GLOBAL_ATTRIBUTE_NUMBER2,",
				"          GLOBAL_ATTRIBUTE_NUMBER3 = DATA_DS.G_1.GLOBAL_ATTRIBUTE_NUMBER3,",
				"          GLOBAL_ATTRIBUTE_NUMBER4 = DATA_DS.G_1.GLOBAL_ATTRIBUTE_NUMBER4,",
				"          GLOBAL_ATTRIBUTE_NUMBER5 = DATA_DS.G_1.GLOBAL_ATTRIBUTE_NUMBER5,",
				"          GOVERNMENT_CONTEXT = DATA_DS.G_1.GOVERNMENT_CONTEXT,",
				"          GROUP_REQUISITIONS = DATA_DS.G_1.GROUP_REQUISITIONS,",
				"          GROUP_REQUISITION_LINES = DATA_DS.G_1.GROUP_REQUISITION_LINES,",
				"          INTERFACE_SOURCE_CODE = DATA_DS.G_1.INTERFACE_SOURCE_CODE,",
				"          JOB_DEFINITION_NAME = DATA_DS.G_1.JOB_DEFINITION_NAME,",
				"          JOB_DEFINITION_PACKAGE = DATA_DS.G_1.JOB_DEFINITION_PACKAGE,",
				"          LAST_BILLED_DATE = DATA_DS.G_1.LAST_BILLED_DATE,",
				"          LAST_RELEASE_DATE = DATA_DS.G_1.LAST_RELEASE_DATE,",
				"          LAST_UPDATED_BY = DATA_DS.G_1.LAST_UPDATED_BY,",
				"          LAST_UPDATED_PROGRAM = DATA_DS.G_1.LAST_UPDATED_PROGRAM,",
				"          LAST_UPDATE_DATE = DATA_DS.G_1.LAST_UPDATE_DATE,",
				"          LAST_UPDATE_LOGIN = DATA_DS.G_1.LAST_UPDATE_LOGIN,",
				"          MASTER_CONTRACT_ID = DATA_DS.G_1.MASTER_CONTRACT_ID,",
				"          MERGE_REQUEST_ID = DATA_DS.G_1.MERGE_REQUEST_ID,",
				"          MIN_RELEASE_AMOUNT = DATA_DS.G_1.MIN_RELEASE_AMOUNT,",
				"          MODE_OF_TRANSPORT = DATA_DS.G_1.MODE_OF_TRANSPORT,",
				"          NOTE_TO_AUTHORIZER = DATA_DS.G_1.NOTE_TO_AUTHORIZER,",
				"          NOTE_TO_RECEIVER = DATA_DS.G_1.NOTE_TO_RECEIVER,",
				"          NOTE_TO_VENDOR = DATA_DS.G_1.NOTE_TO_VENDOR,",
				"          OBJECT_VERSION_NUMBER = DATA_DS.G_1.OBJECT_VERSION_NUMBER,",
				"          ORCHESTRATION_ORDER_FLAG = DATA_DS.G_1.ORCHESTRATION_ORDER_FLAG,",
				"          OVERRIDING_APPROVER_ID = DATA_DS.G_1.OVERRIDING_APPROVER_ID,",
				"          PAY_ON_CODE = DATA_DS.G_1.PAY_ON_CODE,",
				"          PAY_ON_USE_FLAG = DATA_DS.G_1.PAY_ON_USE_FLAG,",
				"          PCARD_ID = DATA_DS.G_1.PCARD_ID,",
				"          PENDING_SIGNATURE_FLAG = DATA_DS.G_1.PENDING_SIGNATURE_FLAG,",
				"          PO_HEADER_ID = DATA_DS.G_1.PO_HEADER_ID,",
				"          PRC_BU_ID = DATA_DS.G_1.PRC_BU_ID,",
				"          PRICE_UPDATE_TOLERANCE = DATA_DS.G_1.PRICE_UPDATE_TOLERANCE,",
				"          PROGRAM_APP_NAME = DATA_DS.G_1.PROGRAM_APP_NAME,",
				"          PROGRAM_NAME = DATA_DS.G_1.PROGRAM_NAME,",
				"          PUNCHOUT_SOURCING_ONLY_FLAG = DATA_DS.G_1.PUNCHOUT_SOURCING_ONLY_FLAG,",
				"          RATE = DATA_DS.G_1.RATE,",
				"          RATE_DATE = DATA_DS.G_1.RATE_DATE,",
				"          RATE_TYPE = DATA_DS.G_1.RATE_TYPE,",
				"          REBUILD_INDEX = DATA_DS.G_1.REBUILD_INDEX,",
				"          REFERENCE_NUM = DATA_DS.G_1.REFERENCE_NUM,",
				"          REFRESH_INDEX = DATA_DS.G_1.REFRESH_INDEX,",
				"          RELEASE_METHOD = DATA_DS.G_1.RELEASE_METHOD,",
				"          REQUEST_ID = DATA_DS.G_1.REQUEST_ID,",
				"          REQ_BU_ID = DATA_DS.G_1.REQ_BU_ID,",
				"          RETRO_PRICE_APPLY_UPDATES_FLAG = DATA_DS.G_1.RETRO_PRICE_APPLY_UPDATES_FLAG,",
				"          RETRO_PRICE_COMM_UPDATES_FLAG = DATA_DS.G_1.RETRO_PRICE_COMM_UPDATES_FLAG,",
				"          RETRO_PRICE_INIT_APPROVAL_FLAG = DATA_DS.G_1.RETRO_PRICE_INIT_APPROVAL_FLAG,",
				"          RETRO_PRICE_OPEN_ORDER_FLAG = DATA_DS.G_1.RETRO_PRICE_OPEN_ORDER_FLAG,",
				"          REVIEW_AUTOGENERATED_RELEASES = DATA_DS.G_1.REVIEW_AUTOGENERATED_RELEASES,",
				"          REVISED_DATE = DATA_DS.G_1.REVISED_DATE,",
				"          REVISION_NUM = DATA_DS.G_1.REVISION_NUM,",
				"          SCHEDULE_GROUP = DATA_DS.G_1.SCHEDULE_GROUP,",
				"          SEGMENT1 = DATA_DS.G_1.SEGMENT1,",
				"          SEGMENT2 = DATA_DS.G_1.SEGMENT2,",
				"          SEGMENT3 = DATA_DS.G_1.SEGMENT3,",
				"          SEGMENT4 = DATA_DS.G_1.SEGMENT4,",
				"          SEGMENT5 = DATA_DS.G_1.SEGMENT5,",
				"          SERVICE_LEVEL = DATA_DS.G_1.SERVICE_LEVEL,",
				"          SHIPPING_CONTROL = DATA_DS.G_1.SHIPPING_CONTROL,",
				"          SHIP_TO_LOCATION_ID = DATA_DS.G_1.SHIP_TO_LOCATION_ID,",
				"          SH_ATTRIBUTE1 = DATA_DS.G_1.SH_ATTRIBUTE1,",
				"          SH_ATTRIBUTE10 = DATA_DS.G_1.SH_ATTRIBUTE10,",
				"          SH_ATTRIBUTE11 = DATA_DS.G_1.SH_ATTRIBUTE11,",
				"          SH_ATTRIBUTE12 = DATA_DS.G_1.SH_ATTRIBUTE12,",
				"          SH_ATTRIBUTE13 = DATA_DS.G_1.SH_ATTRIBUTE13,",
				"          SH_ATTRIBUTE14 = DATA_DS.G_1.SH_ATTRIBUTE14,",
				"          SH_ATTRIBUTE15 = DATA_DS.G_1.SH_ATTRIBUTE15,",
				"          SH_ATTRIBUTE16 = DATA_DS.G_1.SH_ATTRIBUTE16,",
				"          SH_ATTRIBUTE17 = DATA_DS.G_1.SH_ATTRIBUTE17,",
				"          SH_ATTRIBUTE18 = DATA_DS.G_1.SH_ATTRIBUTE18,",
				"          SH_ATTRIBUTE19 = DATA_DS.G_1.SH_ATTRIBUTE19,",
				"          SH_ATTRIBUTE2 = DATA_DS.G_1.SH_ATTRIBUTE2,",
				"          SH_ATTRIBUTE20 = DATA_DS.G_1.SH_ATTRIBUTE20,",
				"          SH_ATTRIBUTE3 = DATA_DS.G_1.SH_ATTRIBUTE3,",
				"          SH_ATTRIBUTE4 = DATA_DS.G_1.SH_ATTRIBUTE4,",
				"          SH_ATTRIBUTE5 = DATA_DS.G_1.SH_ATTRIBUTE5,",
				"          SH_ATTRIBUTE6 = DATA_DS.G_1.SH_ATTRIBUTE6,",
				"          SH_ATTRIBUTE7 = DATA_DS.G_1.SH_ATTRIBUTE7,",
				"          SH_ATTRIBUTE8 = DATA_DS.G_1.SH_ATTRIBUTE8,",
				"          SH_ATTRIBUTE9 = DATA_DS.G_1.SH_ATTRIBUTE9,",
				"          SH_ATTRIBUTE_CATEGORY = DATA_DS.G_1.SH_ATTRIBUTE_CATEGORY,",
				"          SH_ATTRIBUTE_DATE1 = DATA_DS.G_1.SH_ATTRIBUTE_DATE1,",
				"          SH_ATTRIBUTE_DATE10 = DATA_DS.G_1.SH_ATTRIBUTE_DATE10,",
				"          SH_ATTRIBUTE_DATE2 = DATA_DS.G_1.SH_ATTRIBUTE_DATE2,",
				"          SH_ATTRIBUTE_DATE3 = DATA_DS.G_1.SH_ATTRIBUTE_DATE3,",
				"          SH_ATTRIBUTE_DATE4 = DATA_DS.G_1.SH_ATTRIBUTE_DATE4,",
				"          SH_ATTRIBUTE_DATE5 = DATA_DS.G_1.SH_ATTRIBUTE_DATE5,",
				"          SH_ATTRIBUTE_DATE6 = DATA_DS.G_1.SH_ATTRIBUTE_DATE6,",
				"          SH_ATTRIBUTE_DATE7 = DATA_DS.G_1.SH_ATTRIBUTE_DATE7,",
				"          SH_ATTRIBUTE_DATE8 = DATA_DS.G_1.SH_ATTRIBUTE_DATE8,",
				"          SH_ATTRIBUTE_DATE9 = DATA_DS.G_1.SH_ATTRIBUTE_DATE9,",
				"          SH_ATTRIBUTE_NUMBER1 = DATA_DS.G_1.SH_ATTRIBUTE_NUMBER1,",
				"          SH_ATTRIBUTE_NUMBER10 = DATA_DS.G_1.SH_ATTRIBUTE_NUMBER10,",
				"          SH_ATTRIBUTE_NUMBER2 = DATA_DS.G_1.SH_ATTRIBUTE_NUMBER2,",
				"          SH_ATTRIBUTE_NUMBER3 = DATA_DS.G_1.SH_ATTRIBUTE_NUMBER3,",
				"          SH_ATTRIBUTE_NUMBER4 = DATA_DS.G_1.SH_ATTRIBUTE_NUMBER4,",
				"          SH_ATTRIBUTE_NUMBER5 = DATA_DS.G_1.SH_ATTRIBUTE_NUMBER5,",
				"          SH_ATTRIBUTE_NUMBER6 = DATA_DS.G_1.SH_ATTRIBUTE_NUMBER6,",
				"          SH_ATTRIBUTE_NUMBER7 = DATA_DS.G_1.SH_ATTRIBUTE_NUMBER7,",
				"          SH_ATTRIBUTE_NUMBER8 = DATA_DS.G_1.SH_ATTRIBUTE_NUMBER8,",
				"          SH_ATTRIBUTE_NUMBER9 = DATA_DS.G_1.SH_ATTRIBUTE_NUMBER9,",
				"          SH_ATTRIBUTE_TIMESTAMP1 = DATA_DS.G_1.SH_ATTRIBUTE_TIMESTAMP1,",
				"          SH_ATTRIBUTE_TIMESTAMP10 = DATA_DS.G_1.SH_ATTRIBUTE_TIMESTAMP10,",
				"          SH_ATTRIBUTE_TIMESTAMP2 = DATA_DS.G_1.SH_ATTRIBUTE_TIMESTAMP2,",
				"          SH_ATTRIBUTE_TIMESTAMP3 = DATA_DS.G_1.SH_ATTRIBUTE_TIMESTAMP3,",
				"          SH_ATTRIBUTE_TIMESTAMP4 = DATA_DS.G_1.SH_ATTRIBUTE_TIMESTAMP4,",
				"          SH_ATTRIBUTE_TIMESTAMP5 = DATA_DS.G_1.SH_ATTRIBUTE_TIMESTAMP5,",
				"          SH_ATTRIBUTE_TIMESTAMP6 = DATA_DS.G_1.SH_ATTRIBUTE_TIMESTAMP6,",
				"          SH_ATTRIBUTE_TIMESTAMP7 = DATA_DS.G_1.SH_ATTRIBUTE_TIMESTAMP7,",
				"          SH_ATTRIBUTE_TIMESTAMP8 = DATA_DS.G_1.SH_ATTRIBUTE_TIMESTAMP8,",
				"          SH_ATTRIBUTE_TIMESTAMP9 = DATA_DS.G_1.SH_ATTRIBUTE_TIMESTAMP9,",
				"          SIGNATURE_REQUIRED_FLAG = DATA_DS.G_1.SIGNATURE_REQUIRED_FLAG,",
				"          SKIP_ELECTRONIC_COMM_FLAG = DATA_DS.G_1.SKIP_ELECTRONIC_COMM_FLAG,",
				"          SOLDTO_BU_ID = DATA_DS.G_1.SOLDTO_BU_ID,",
				"          SOLDTO_LE_ID = DATA_DS.G_1.SOLDTO_LE_ID,",
				"          SOURCING_PRIORITY = DATA_DS.G_1.SOURCING_PRIORITY,",
				"          SPECIAL_HANDLING_TYPE_CODE = DATA_DS.G_1.SPECIAL_HANDLING_TYPE_CODE,",
				"          START_DATE = DATA_DS.G_1.START_DATE,",
				"          STYLE_ID = DATA_DS.G_1.STYLE_ID,",
				"          SUBMIT_APPROVAL_AUTOMATIC = DATA_DS.G_1.SUBMIT_APPROVAL_AUTOMATIC,",
				"          SUBMIT_DATE = DATA_DS.G_1.SUBMIT_DATE,",
				"          SUMMARY_FLAG = DATA_DS.G_1.SUMMARY_FLAG,",
				"          SUPPLIER_NOTIF_METHOD = DATA_DS.G_1.SUPPLIER_NOTIF_METHOD,",
				"          TAX_ATTRIBUTE_UPDATE_CODE = DATA_DS.G_1.TAX_ATTRIBUTE_UPDATE_CODE,",
				"          TAX_DOCUMENT_SUBTYPE = DATA_DS.G_1.TAX_DOCUMENT_SUBTYPE,",
				"          TERMS_ID = DATA_DS.G_1.TERMS_ID,",
				"          THIRD_PTY_REG_ID = DATA_DS.G_1.THIRD_PTY_REG_ID,",
				"          TYPE_LOOKUP_CODE = DATA_DS.G_1.TYPE_LOOKUP_CODE,",
				"          UPDATE_SOURCING_RULES_FLAG = DATA_DS.G_1.UPDATE_SOURCING_RULES_FLAG,",
				"          USE_NEED_BY_DATE = DATA_DS.G_1.USE_NEED_BY_DATE,",
				"          USE_ORDER_DATE_IN_PRICING_FLAG = DATA_DS.G_1.USE_ORDER_DATE_IN_PRICING_FLAG,",
				"          USE_SALES_ORDER_NUMBER_FLAG = DATA_DS.G_1.USE_SALES_ORDER_NUMBER_FLAG,",
				"          USE_SHIP_TO = DATA_DS.G_1.USE_SHIP_TO,",
				"          USE_SHIP_TO_FOR_GROUP_REQS = DATA_DS.G_1.USE_SHIP_TO_FOR_GROUP_REQS,",
				"          VENDOR_CONTACT_ID = DATA_DS.G_1.VENDOR_CONTACT_ID,",
				"          VENDOR_ID = DATA_DS.G_1.VENDOR_ID,",
				"          VENDOR_ORDER_NUM = DATA_DS.G_1.VENDOR_ORDER_NUM,",
				"          VENDOR_SITE_ID = DATA_DS.G_1.VENDOR_SITE_ID,",
				"          XML_CHANGE_SEND_DATE = DATA_DS.G_1.XML_CHANGE_SEND_DATE,",
				"          XML_FLAG = DATA_DS.G_1.XML_FLAG,",
				"          XML_SEND_DATE = DATA_DS.G_1.XML_SEND_DATE",
				"     ),",
				"     skipDuplicateMapInputs: true,",
				"     skipDuplicateMapOutputs: true) ~> XmlToCsvflatten",
				"XmlToCsvflatten derive(source_name = 'SYSTEM',",
				"          sub_source_name = 'R2P',",
				"          created_date_time = currentUTC()) ~> addLoadDetails",
				"addLoadDetails sink(allowSchemaDrift: true,",
				"     validateSchema: false,",
				"     partitionFileNames:['Po_Headers_All.csv'],",
				"     umask: 0022,",
				"     preCommands: [],",
				"     postCommands: [],",
				"     skipDuplicateMapInputs: true,",
				"     skipDuplicateMapOutputs: true,",
				"     partitionBy('hash', 1)) ~> SnkCsv"
			]
		}
	}
}