{
	"name": "pl_ced_idocs_master",
	"properties": {
		"activities": [
			{
				"name": "pl_idocs_doc_eng_master_pipeline",
				"type": "ExecutePipeline",
				"dependsOn": [],
				"policy": {
					"secureInput": false
				},
				"userProperties": [],
				"typeProperties": {
					"pipeline": {
						"referenceName": "pl_idocs_doc_eng_master_pipeline",
						"type": "PipelineReference"
					},
					"waitOnCompletion": true,
					"parameters": {
						"p_pl_m_sourcefolder": {
							"value": "iDocs_360536",
							"type": "Expression"
						}
					}
				}
			},
			{
				"name": "pl_idocs_doc_ven_master_pipeline",
				"type": "ExecutePipeline",
				"dependsOn": [
					{
						"activity": "pl_idocs_doc_eng_master_pipeline",
						"dependencyConditions": [
							"Completed"
						]
					}
				],
				"policy": {
					"secureInput": false
				},
				"userProperties": [],
				"typeProperties": {
					"pipeline": {
						"referenceName": "pl_idocs_doc_ven_master_pipeline",
						"type": "PipelineReference"
					},
					"waitOnCompletion": true,
					"parameters": {
						"p_pl_m_sourcefolder": {
							"value": "iDocs_360536",
							"type": "Expression"
						}
					}
				}
			}
		],
		"folder": {
			"name": "Projects/Central Engineering Database/iDocs"
		},
		"annotations": []
	}
}