{
	"name": "pl_ced_oracle_spi_bal_spi_equip",
	"properties": {
		"activities": [
			{
				"name": "cd_src_to_stage",
				"type": "Copy",
				"dependsOn": [
					{
						"activity": "lk_get_pipeline_email_parameters",
						"dependencyConditions": [
							"Succeeded"
						]
					},
					{
						"activity": "lk_get_pipeline_parameters",
						"dependencyConditions": [
							"Succeeded"
						]
					}
				],
				"policy": {
					"timeout": "0.12:00:00",
					"retry": 0,
					"retryIntervalInSeconds": 30,
					"secureOutput": false,
					"secureInput": false
				},
				"userProperties": [],
				"typeProperties": {
					"source": {
						"type": "OracleSource",
						"partitionOption": "None",
						"numberPrecision": 38,
						"numberScale": 18,
						"queryTimeout": "02:00:00"
					},
					"sink": {
						"type": "ParquetSink",
						"storeSettings": {
							"type": "AzureBlobFSWriteSettings"
						},
						"formatSettings": {
							"type": "ParquetWriteSettings"
						}
					},
					"enableStaging": false,
					"translator": {
						"type": "TabularTranslator",
						"mappings": [
							{
								"source": {
									"name": "CMPNT_ID",
									"type": "String"
								},
								"sink": {
									"name": "CMPNT_ID",
									"type": "String",
									"physicalType": "UTF8"
								}
							},
							{
								"source": {
									"name": "PAU",
									"type": "String"
								},
								"sink": {
									"name": "PAU",
									"type": "String",
									"physicalType": "UTF8"
								}
							},
							{
								"source": {
									"name": "SPI_TAG",
									"type": "String"
								},
								"sink": {
									"name": "SPI_TAG",
									"type": "String",
									"physicalType": "UTF8"
								}
							},
							{
								"source": {
									"name": "RDSPP_TAG",
									"type": "String"
								},
								"sink": {
									"name": "RDSPP_TAG",
									"type": "String",
									"physicalType": "UTF8"
								}
							},
							{
								"source": {
									"name": "I_TYPE",
									"type": "String"
								},
								"sink": {
									"name": "I_TYPE",
									"type": "String",
									"physicalType": "UTF8"
								}
							},
							{
								"source": {
									"name": "TAG_SERVICE",
									"type": "String"
								},
								"sink": {
									"name": "TAG_SERVICE",
									"type": "String",
									"physicalType": "UTF8"
								}
							},
							{
								"source": {
									"name": "LOCATION",
									"type": "String"
								},
								"sink": {
									"name": "LOCATION",
									"type": "String",
									"physicalType": "UTF8"
								}
							},
							{
								"source": {
									"name": "PID",
									"type": "String"
								},
								"sink": {
									"name": "PID",
									"type": "String",
									"physicalType": "UTF8"
								}
							},
							{
								"source": {
									"name": "SCOPE",
									"type": "String"
								},
								"sink": {
									"name": "SCOPE",
									"type": "String",
									"physicalType": "UTF8"
								}
							},
							{
								"source": {
									"name": "REQ",
									"type": "String"
								},
								"sink": {
									"name": "REQ",
									"type": "String",
									"physicalType": "UTF8"
								}
							},
							{
								"source": {
									"name": "SOI",
									"type": "String"
								},
								"sink": {
									"name": "SOI",
									"type": "String",
									"physicalType": "UTF8"
								}
							},
							{
								"source": {
									"name": "POI",
									"type": "String"
								},
								"sink": {
									"name": "POI",
									"type": "String",
									"physicalType": "UTF8"
								}
							},
							{
								"source": {
									"name": "DISCIPLINE",
									"type": "String"
								},
								"sink": {
									"name": "DISCIPLINE",
									"type": "String",
									"physicalType": "UTF8"
								}
							},
							{
								"source": {
									"name": "MANUFACTURERNAME",
									"type": "String"
								},
								"sink": {
									"name": "MANUFACTURER_NAME",
									"physicalType": "UTF8"
								}
							},
							{
								"source": {
									"name": "MODELNAME",
									"type": "String"
								},
								"sink": {
									"name": "MODEL_NAME",
									"physicalType": "UTF8"
								}
							},
							{
								"source": {
									"name": "SERIALNUMBER",
									"type": "String"
								},
								"sink": {
									"name": "SERIAL_NUMBER",
									"physicalType": "UTF8"
								}
							},
							{
								"source": {
									"name": "EQA_DECK",
									"type": "String"
								},
								"sink": {
									"name": "EQA_DECK",
									"type": "String",
									"physicalType": "UTF8"
								}
							},
							{
								"source": {
									"name": "EQA_ROOM",
									"type": "String"
								},
								"sink": {
									"name": "EQA_ROOM",
									"type": "String",
									"physicalType": "UTF8"
								}
							},
							{
								"source": {
									"name": "RDS_CODE",
									"type": "String"
								},
								"sink": {
									"name": "RDS_CODE",
									"type": "String",
									"physicalType": "UTF8"
								}
							}
						],
						"typeConversion": true,
						"typeConversionSettings": {
							"allowDataTruncation": true,
							"treatBooleanAsNumber": false
						}
					}
				},
				"inputs": [
					{
						"referenceName": "ds_CED_tennet_2gw_hag_oracledb02_spf09nlp",
						"type": "DatasetReference",
						"parameters": {
							"table_schema": {
								"value": "@activity('lk_get_pipeline_parameters').output.firstRow.table_schema",
								"type": "Expression"
							},
							"table_name": {
								"value": "@activity('lk_get_pipeline_parameters').output.firstRow.table_name",
								"type": "Expression"
							},
							"server_name": {
								"value": "@activity('lk_get_pipeline_parameters').output.firstRow.server_name",
								"type": "Expression"
							},
							"port": {
								"value": "@activity('lk_get_pipeline_parameters').output.firstRow.port",
								"type": "Expression"
							},
							"database_name": {
								"value": "@activity('lk_get_pipeline_parameters').output.firstRow.database_name",
								"type": "Expression"
							}
						}
					}
				],
				"outputs": [
					{
						"referenceName": "ds_adlsg2_parquet_generic",
						"type": "DatasetReference",
						"parameters": {
							"file_system": {
								"value": "@activity('lk_get_pipeline_parameters').output.firstRow.file_system",
								"type": "Expression"
							},
							"directory": {
								"value": "@activity('lk_get_pipeline_parameters').output.firstRow.directory",
								"type": "Expression"
							},
							"file_name": {
								"value": "@concat(activity('lk_get_pipeline_parameters').output.firstRow.file_name,'.parquet')",
								"type": "Expression"
							}
						}
					}
				]
			},
			{
				"name": "cd_stg_to_synapse",
				"type": "Copy",
				"dependsOn": [
					{
						"activity": "cd_src_to_stage",
						"dependencyConditions": [
							"Succeeded"
						]
					}
				],
				"policy": {
					"timeout": "0.12:00:00",
					"retry": 0,
					"retryIntervalInSeconds": 30,
					"secureOutput": false,
					"secureInput": false
				},
				"userProperties": [],
				"typeProperties": {
					"source": {
						"type": "ParquetSource",
						"additionalColumns": [
							{
								"name": "Load_date",
								"value": {
									"value": "@activity('lk_get_pipeline_parameters').output.firstRow.run_start_datetime",
									"type": "Expression"
								}
							}
						],
						"storeSettings": {
							"type": "AzureBlobFSReadSettings",
							"recursive": true,
							"enablePartitionDiscovery": false
						},
						"formatSettings": {
							"type": "ParquetReadSettings"
						}
					},
					"sink": {
						"type": "SqlDWSink",
						"preCopyScript": {
							"value": "INSERT INTO @{concat(activity('lk_get_pipeline_parameters').output.firstRow.target_table,'_archive')} SELECT * FROM @{activity('lk_get_pipeline_parameters').output.firstRow.target_table};\n \nTRUNCATE TABLE @{activity('lk_get_pipeline_parameters').output.firstRow.target_table};\n \nDELETE FROM @{concat(activity('lk_get_pipeline_parameters').output.firstRow.target_table,'_archive')}\nWHERE Load_date < DATEADD(MONTH, -6, GETDATE());",
							"type": "Expression"
						},
						"allowCopyCommand": true,
						"disableMetricsCollection": false
					},
					"enableStaging": true,
					"stagingSettings": {
						"linkedServiceName": {
							"referenceName": "ADLSG2 TimeAnalytics DEV",
							"type": "LinkedServiceReference"
						},
						"path": "mdr-raw-data/ Polybase_Staging_Space",
						"enableCompression": true
					},
					"translator": {
						"type": "TabularTranslator",
						"mappings": [
							{
								"source": {
									"name": "CMPNT_ID",
									"type": "String"
								},
								"sink": {
									"name": "CMPNT_ID",
									"type": "String"
								}
							},
							{
								"source": {
									"name": "PAU",
									"type": "String"
								},
								"sink": {
									"name": "PAU",
									"type": "String"
								}
							},
							{
								"source": {
									"name": "SPI_TAG",
									"type": "String"
								},
								"sink": {
									"name": "SPI_TAG",
									"type": "String"
								}
							},
							{
								"source": {
									"name": "RDSPP_TAG",
									"type": "String"
								},
								"sink": {
									"name": "RDSPP_TAG",
									"type": "String"
								}
							},
							{
								"source": {
									"name": "I_TYPE",
									"type": "String"
								},
								"sink": {
									"name": "I_TYPE",
									"type": "String"
								}
							},
							{
								"source": {
									"name": "TAG_SERVICE",
									"type": "String"
								},
								"sink": {
									"name": "TAG_SERVICE",
									"type": "String"
								}
							},
							{
								"source": {
									"name": "LOCATION",
									"type": "String"
								},
								"sink": {
									"name": "LOCATION",
									"type": "String"
								}
							},
							{
								"source": {
									"name": "PID",
									"type": "String"
								},
								"sink": {
									"name": "PID",
									"type": "String"
								}
							},
							{
								"source": {
									"name": "SCOPE",
									"type": "String"
								},
								"sink": {
									"name": "SCOPE",
									"type": "String"
								}
							},
							{
								"source": {
									"name": "REQ",
									"type": "String"
								},
								"sink": {
									"name": "REQ",
									"type": "String"
								}
							},
							{
								"source": {
									"name": "SOI",
									"type": "String"
								},
								"sink": {
									"name": "SOI",
									"type": "String"
								}
							},
							{
								"source": {
									"name": "POI",
									"type": "String"
								},
								"sink": {
									"name": "POI",
									"type": "String"
								}
							},
							{
								"source": {
									"name": "DISCIPLINE",
									"type": "String"
								},
								"sink": {
									"name": "DISCIPLINE",
									"type": "String"
								}
							},
							{
								"source": {
									"name": "MANUFACTURER_NAME",
									"type": "String"
								},
								"sink": {
									"name": "MANUFACTURER_NAME",
									"type": "String"
								}
							},
							{
								"source": {
									"name": "MODEL_NAME",
									"type": "String"
								},
								"sink": {
									"name": "MODEL_NAME",
									"type": "String"
								}
							},
							{
								"source": {
									"name": "SERIAL_NUMBER",
									"type": "String"
								},
								"sink": {
									"name": "SERIAL_NUMBER",
									"type": "String"
								}
							},
							{
								"source": {
									"name": "EQA_DECK",
									"type": "String"
								},
								"sink": {
									"name": "EQA_DECK",
									"type": "String"
								}
							},
							{
								"source": {
									"name": "EQA_ROOM",
									"type": "String"
								},
								"sink": {
									"name": "EQA_ROOM",
									"type": "String"
								}
							},
							{
								"source": {
									"name": "RDS_CODE",
									"type": "String"
								},
								"sink": {
									"name": "RDS_CODE",
									"type": "String"
								}
							},
							{
								"source": {
									"name": "Load_date",
									"type": "String"
								},
								"sink": {
									"name": "Load_date",
									"type": "DateTime"
								}
							}
						]
					}
				},
				"inputs": [
					{
						"referenceName": "ds_adlsg2_parquet_generic",
						"type": "DatasetReference",
						"parameters": {
							"file_system": {
								"value": "@activity('lk_get_pipeline_parameters').output.firstRow.file_system",
								"type": "Expression"
							},
							"directory": {
								"value": "@activity('lk_get_pipeline_parameters').output.firstRow.directory",
								"type": "Expression"
							},
							"file_name": {
								"value": "@concat(activity('lk_get_pipeline_parameters').output.firstRow.file_name,'.parquet')",
								"type": "Expression"
							}
						}
					}
				],
				"outputs": [
					{
						"referenceName": "AzureSynapseAnalyticsPool",
						"type": "DatasetReference",
						"parameters": {
							"schema": {
								"value": "@split(activity('lk_get_pipeline_parameters').output.firstRow.target_table,'.')[0]",
								"type": "Expression"
							},
							"TableName": {
								"value": "@split(activity('lk_get_pipeline_parameters').output.firstRow.target_table,'.')[1]",
								"type": "Expression"
							}
						}
					}
				]
			},
			{
				"name": "lk_get_pipeline_email_parameters",
				"description": "Get the parameters to be used in this pipeline",
				"type": "Lookup",
				"dependsOn": [],
				"policy": {
					"timeout": "7.00:00:00",
					"retry": 0,
					"retryIntervalInSeconds": 30,
					"secureOutput": false,
					"secureInput": false
				},
				"userProperties": [],
				"typeProperties": {
					"source": {
						"type": "SqlDWSource",
						"sqlReaderStoredProcedureName": "getPipelineParametersValues",
						"storedProcedureParameters": {
							"pPipelineCode": {
								"type": "String",
								"value": {
									"value": "pl_ced_master_email",
									"type": "Expression"
								}
							},
							"pPipeLineSubCode": {
								"type": "String",
								"value": {
									"value": "CED",
									"type": "Expression"
								}
							}
						},
						"queryTimeout": "02:00:00",
						"partitionOption": "None"
					},
					"dataset": {
						"referenceName": "ds_azure_synapse_parameter",
						"type": "DatasetReference"
					}
				}
			},
			{
				"name": "Append STG to Synapse Error",
				"type": "AppendVariable",
				"dependsOn": [
					{
						"activity": "cd_stg_to_synapse",
						"dependencyConditions": [
							"Failed"
						]
					}
				],
				"userProperties": [],
				"typeProperties": {
					"variableName": "v_error_message",
					"value": {
						"value": "@concat('Stage to Synapse | ',\nactivity('cd_stg_to_synapse').output.errors[0].Code,' | ',\nactivity('cd_stg_to_synapse').output.errors[0].Message)",
						"type": "Expression"
					}
				}
			},
			{
				"name": "If failure detected send mail",
				"type": "IfCondition",
				"dependsOn": [
					{
						"activity": "Append SP Error",
						"dependencyConditions": [
							"Skipped",
							"Completed"
						]
					},
					{
						"activity": "sp_dataload_status",
						"dependencyConditions": [
							"Skipped",
							"Completed"
						]
					}
				],
				"userProperties": [],
				"typeProperties": {
					"expression": {
						"value": "@if(empty(variables('v_error_message')),false,true)",
						"type": "Expression"
					},
					"ifTrueActivities": [
						{
							"name": "Send Email On Failure",
							"type": "WebActivity",
							"dependsOn": [],
							"policy": {
								"timeout": "7.00:00:00",
								"retry": 0,
								"retryIntervalInSeconds": 30,
								"secureOutput": false,
								"secureInput": false
							},
							"userProperties": [],
							"typeProperties": {
								"method": "POST",
								"headers": {
									"Content-Type": "application/json"
								},
								"url": "https://prod-31.eastus.logic.azure.com:443/workflows/03d7da5abbab4215a05aeaceae3b96fa/triggers/manual/paths/invoke?api-version=2016-10-01&sp=%2Ftriggers%2Fmanual%2Frun&sv=1.0&sig=asuyutHtoSxGFURsj1-A6AKRiNLdXZ4mTnZvZ17_8hI",
								"connectVia": {
									"referenceName": "integrationRuntimeEast2",
									"type": "IntegrationRuntimeReference"
								},
								"body": {
									"value": "{\n    \"DataFactoryName\": \"@{pipeline().DataFactory}\",\n    \"PipelineName\": \"@{pipeline().Pipeline}\",\n    \"Activity\": \"@{split(replace(replace(join(variables('v_error_message'),';'),'\"',''),'\\','/'),'|')[0]}\",\n    \"ErrorMessage\": \"@{split(replace(replace(join(variables('v_error_message'),';'),'\"',''),'\\','/'),'|')[2]}\",\n\"EmailTo\": \"@{activity('lk_get_pipeline_email_parameters').output.firstRow.master_pipeline_email}\"\n}",
									"type": "Expression"
								}
							}
						}
					]
				}
			},
			{
				"name": "lk_get_pipeline_parameters",
				"description": "Get the parameters to be used in this pipeline",
				"type": "Lookup",
				"dependsOn": [],
				"policy": {
					"timeout": "7.00:00:00",
					"retry": 0,
					"retryIntervalInSeconds": 30,
					"secureOutput": false,
					"secureInput": false
				},
				"userProperties": [],
				"typeProperties": {
					"source": {
						"type": "SqlDWSource",
						"sqlReaderStoredProcedureName": "getPipelineParametersValues",
						"storedProcedureParameters": {
							"pPipelineCode": {
								"type": "String",
								"value": {
									"value": "@pipeline().Pipeline",
									"type": "Expression"
								}
							},
							"pPipeLineSubCode": {
								"type": "String",
								"value": {
									"value": "Oracle_DB",
									"type": "Expression"
								}
							}
						},
						"queryTimeout": "02:00:00",
						"partitionOption": "None"
					},
					"dataset": {
						"referenceName": "ds_azure_synapse_parameter",
						"type": "DatasetReference"
					}
				}
			},
			{
				"name": "Append SRC to STG Error",
				"type": "AppendVariable",
				"dependsOn": [
					{
						"activity": "cd_src_to_stage",
						"dependencyConditions": [
							"Failed"
						]
					}
				],
				"userProperties": [],
				"typeProperties": {
					"variableName": "v_error_message",
					"value": {
						"value": "@concat('Source to Stage | ',\nactivity('cd_src_to_stage').output.errors[0].Code,' | ',\nactivity('cd_src_to_stage').output.errors[0].Message)",
						"type": "Expression"
					}
				}
			},
			{
				"name": "sp_dataload_status",
				"type": "SqlServerStoredProcedure",
				"dependsOn": [
					{
						"activity": "cd_stg_to_synapse",
						"dependencyConditions": [
							"Succeeded"
						]
					}
				],
				"policy": {
					"timeout": "7.00:00:00",
					"retry": 0,
					"retryIntervalInSeconds": 30,
					"secureOutput": false,
					"secureInput": false
				},
				"userProperties": [],
				"typeProperties": {
					"storedProcedureName": {
						"value": "[edw].data_warehouse_dataload_status",
						"type": "Expression"
					},
					"storedProcedureParameters": {
						"datasource": {
							"value": {
								"value": "@activity('lk_get_pipeline_parameters').output.firstRow.database_name",
								"type": "Expression"
							},
							"type": "String"
						},
						"description": {
							"value": {
								"value": "@activity('lk_get_pipeline_parameters').output.firstRow.description",
								"type": "Expression"
							},
							"type": "String"
						},
						"load_date_time": {
							"value": {
								"value": "@activity('lk_get_pipeline_parameters').output.firstRow.run_start_datetime",
								"type": "Expression"
							},
							"type": "DateTime"
						},
						"project_number": {
							"value": {
								"value": "@pipeline().parameters.pProjectNumber",
								"type": "Expression"
							},
							"type": "String"
						},
						"table_name": {
							"value": {
								"value": "@activity('lk_get_pipeline_parameters').output.firstRow.target_table",
								"type": "Expression"
							},
							"type": "String"
						}
					}
				},
				"linkedServiceName": {
					"referenceName": "linkedservice_DEV_entanalytics_synapse",
					"type": "LinkedServiceReference"
				}
			},
			{
				"name": "Append SP Error",
				"type": "AppendVariable",
				"dependsOn": [
					{
						"activity": "sp_dataload_status",
						"dependencyConditions": [
							"Failed"
						]
					}
				],
				"userProperties": [],
				"typeProperties": {
					"variableName": "v_error_message",
					"value": {
						"value": "@concat('sp_dataload_status Failure: | |',\nactivity('sp_dataload_status').error.message)\n",
						"type": "Expression"
					}
				}
			}
		],
		"parameters": {
			"pPipeLineSubCode": {
				"type": "string",
				"defaultValue": "Oracle_DB"
			},
			"pProjectNumber": {
				"type": "string",
				"defaultValue": "360536"
			}
		},
		"variables": {
			"v_error_message": {
				"type": "Array"
			}
		},
		"folder": {
			"name": "Projects/Central Engineering Database/Oracle DB"
		},
		"annotations": []
	}
}