{
	"name": "pl_Master_pipeline_New_ESR_Daily_Runs",
	"properties": {
		"activities": [
			{
				"name": "Execute Pipeline1",
				"type": "ExecutePipeline",
				"dependsOn": [],
				"policy": {
					"secureInput": false
				},
				"userProperties": [],
				"typeProperties": {
					"pipeline": {
						"referenceName": "pl_BIR_Global_Expediting_Report_Direct_New_All_Projects",
						"type": "PipelineReference"
					},
					"waitOnCompletion": true,
					"parameters": {
						"proj_id": "D7507"
					}
				}
			},
			{
				"name": "Execute Pipeline2",
				"type": "ExecutePipeline",
				"dependsOn": [
					{
						"activity": "Execute Pipeline1",
						"dependencyConditions": [
							"Succeeded"
						]
					}
				],
				"policy": {
					"secureInput": false
				},
				"userProperties": [],
				"typeProperties": {
					"pipeline": {
						"referenceName": "pl_BIR_Global_Expediting_Report_Direct_New_All_Projects",
						"type": "PipelineReference"
					},
					"waitOnCompletion": true,
					"parameters": {
						"proj_id": "D7519"
					}
				}
			},
			{
				"name": "Execute Pipeline4",
				"type": "ExecutePipeline",
				"dependsOn": [
					{
						"activity": "Execute Pipeline3",
						"dependencyConditions": [
							"Succeeded"
						]
					}
				],
				"policy": {
					"secureInput": false
				},
				"userProperties": [],
				"typeProperties": {
					"pipeline": {
						"referenceName": "pl_BIR_Global_Expediting_Report_Direct_New_All_Projects",
						"type": "PipelineReference"
					},
					"waitOnCompletion": true,
					"parameters": {
						"proj_id": "D7440"
					}
				}
			},
			{
				"name": "Execute Pipeline5",
				"type": "ExecutePipeline",
				"dependsOn": [
					{
						"activity": "Execute Pipeline4",
						"dependencyConditions": [
							"Succeeded"
						]
					}
				],
				"policy": {
					"secureInput": false
				},
				"userProperties": [],
				"typeProperties": {
					"pipeline": {
						"referenceName": "pl_BIR_Global_Expediting_Report_Direct_New_All_Projects",
						"type": "PipelineReference"
					},
					"waitOnCompletion": true,
					"parameters": {
						"proj_id": "D7650"
					}
				}
			},
			{
				"name": "Execute Pipeline3",
				"type": "ExecutePipeline",
				"dependsOn": [
					{
						"activity": "Execute Pipeline2",
						"dependencyConditions": [
							"Succeeded"
						]
					}
				],
				"policy": {
					"secureInput": false
				},
				"userProperties": [],
				"typeProperties": {
					"pipeline": {
						"referenceName": "pl_BIR_Global_Expediting_Report_Direct_New_All_Projects",
						"type": "PipelineReference"
					},
					"waitOnCompletion": true,
					"parameters": {
						"proj_id": "D7264"
					}
				}
			},
			{
				"name": "Execute Pipeline6",
				"type": "ExecutePipeline",
				"dependsOn": [
					{
						"activity": "Execute Pipeline5",
						"dependencyConditions": [
							"Succeeded"
						]
					}
				],
				"policy": {
					"secureInput": false
				},
				"userProperties": [],
				"typeProperties": {
					"pipeline": {
						"referenceName": "pl_BIR_Global_Expediting_Report_Direct_New_All_Projects",
						"type": "PipelineReference"
					},
					"waitOnCompletion": true,
					"parameters": {
						"proj_id": "D7506"
					}
				}
			},
			{
				"name": "Execute Pipeline7",
				"type": "ExecutePipeline",
				"dependsOn": [
					{
						"activity": "Execute Pipeline6",
						"dependencyConditions": [
							"Succeeded"
						]
					}
				],
				"policy": {
					"secureInput": false
				},
				"userProperties": [],
				"typeProperties": {
					"pipeline": {
						"referenceName": "pl_BIR_Global_Expediting_Report_Direct_New_All_Projects",
						"type": "PipelineReference"
					},
					"waitOnCompletion": true,
					"parameters": {
						"proj_id": "D7560"
					}
				}
			},
			{
				"name": "Execute Pipeline8",
				"type": "ExecutePipeline",
				"dependsOn": [
					{
						"activity": "Execute Pipeline7",
						"dependencyConditions": [
							"Succeeded"
						]
					}
				],
				"policy": {
					"secureInput": false
				},
				"userProperties": [],
				"typeProperties": {
					"pipeline": {
						"referenceName": "pl_BIR_Global_Expediting_Report_Direct_New_All_Projects",
						"type": "PipelineReference"
					},
					"waitOnCompletion": true,
					"parameters": {
						"proj_id": "D7317"
					}
				}
			},
			{
				"name": "Execute Pipeline9",
				"type": "ExecutePipeline",
				"dependsOn": [
					{
						"activity": "Execute Pipeline8",
						"dependencyConditions": [
							"Succeeded"
						]
					}
				],
				"policy": {
					"secureInput": false
				},
				"userProperties": [],
				"typeProperties": {
					"pipeline": {
						"referenceName": "pl_BIR_Global_Expediting_Report_Direct_New_All_Projects",
						"type": "PipelineReference"
					},
					"waitOnCompletion": true,
					"parameters": {
						"proj_id": "D7555"
					}
				}
			}
		],
		"folder": {
			"name": "Projects/NCSA/Ruya_D7507"
		},
		"annotations": []
	}
}