{
	"name": "ds_AzureSynapseAnalytics_subcontract_employee_stage",
	"properties": {
		"linkedServiceName": {
			"referenceName": "linkedservice_DEV_entanalytics_synapse",
			"type": "LinkedServiceReference"
		},
		"annotations": [],
		"type": "AzureSqlDWTable",
		"schema": [
			{
				"name": "EmplId",
				"type": "varchar"
			},
			{
				"name": "Name",
				"type": "varchar"
			},
			{
				"name": "CompanyCode",
				"type": "varchar"
			},
			{
				"name": "CompanyName",
				"type": "varchar"
			},
			{
				"name": "JobClass",
				"type": "varchar"
			},
			{
				"name": "WorkDate",
				"type": "varchar"
			},
			{
				"name": "DailyHours",
				"type": "varchar"
			}
		],
		"typeProperties": {
			"schema": "gpd",
			"table": "NCSA_SubcontractEmployee"
		}
	},
	"type": "Microsoft.DataFactory/factories/datasets"
}