{
	"name": "ds_adlsg2_csv_contracts_mcpm_raw",
	"properties": {
		"linkedServiceName": {
			"referenceName": "ADLSG2 TimeAnalytics DEV",
			"type": "LinkedServiceReference"
		},
		"folder": {
			"name": "Projects/NCSA/Phases"
		},
		"annotations": [],
		"type": "DelimitedText",
		"typeProperties": {
			"location": {
				"type": "AzureBlobFSLocation",
				"folderPath": "Project_Data/NCSA/MCPM/Contracts",
				"fileSystem": "mdr-raw-data"
			},
			"columnDelimiter": ",",
			"escapeChar": "\\",
			"firstRowAsHeader": true,
			"quoteChar": "\""
		},
		"schema": [
			{
				"name": "project_id",
				"type": "String"
			},
			{
				"name": "contractno",
				"type": "String"
			},
			{
				"name": "location",
				"type": "String"
			},
			{
				"name": "Entity",
				"type": "String"
			}
		]
	},
	"type": "Microsoft.DataFactory/factories/datasets"
}