{
	"name": "ds_generic_yardkpi_fss",
	"properties": {
		"linkedServiceName": {
			"referenceName": "ls_generic_yardkpi_fss",
			"type": "LinkedServiceReference"
		},
		"parameters": {
			"Container": {
				"type": "string"
			},
			"File": {
				"type": "string"
			},
			"Directory": {
				"type": "string"
			}
		},
		"annotations": [],
		"type": "DelimitedText",
		"typeProperties": {
			"location": {
				"type": "AzureBlobStorageLocation",
				"fileName": {
					"value": "@dataset().File",
					"type": "Expression"
				},
				"folderPath": {
					"value": "@dataset().Directory",
					"type": "Expression"
				},
				"container": {
					"value": "@dataset().Container",
					"type": "Expression"
				}
			},
			"columnDelimiter": ",",
			"escapeChar": "\\",
			"firstRowAsHeader": true,
			"quoteChar": "\""
		},
		"schema": []
	},
	"type": "Microsoft.DataFactory/factories/datasets"
}